[{"word":"give away","phonetics":[],"meanings":[{"partOfSpeech":"verb","definitions":[{"definition":"To make a gift of (something).","synonyms":[],"antonyms":[],"example":"I didn't like that book, so I gave it away."},{"definition":"To relinquish control over.","synonyms":[],"antonyms":[]},{"definition":"To formally hand over a bride to the bridegroom; often by her father.","synonyms":[],"antonyms":[],"example":"Who giveth away this woman to this man in Holy matrimony?"},{"definition":"(sometimes reflexive) To unintentionally reveal a secret, divulge undisclosed information, or expose someone.","synonyms":[],"antonyms":[],"example":"He gave away his hiding place when he accidentally sneezed."},{"definition":"To concede an advantage in weight, time, height etc.","synonyms":[],"antonyms":[],"example":"Despite giving away twenty pounds in weight, the challenger found a knock-out blow in the second round."},{"definition":"To concede.","synonyms":[],"antonyms":[]}],"synonyms":[],"antonyms":[]}],"license":{"name":"CC BY-SA 3.0","url":"https://creativecommons.org/licenses/by-sa/3.0"},"sourceUrls":["https://en.wiktionary.org/wiki/give%20away"]}]